{
  "m_GameObject": {
    "m_FileID": 0,
    "m_PathID": 0
  },
  "m_Enabled": 1,
  "m_Script": {
    "m_FileID": 0,
    "m_PathID": 3316481456837282111
  },
  "m_Name": "news_data",
  "table": [
    {
      "id": 1,
      "date": "2022/03/14 13:00",
      "tag": 7,
      "title": "アーリーアクセス開始のお知らせ",
      "message": "「モンスター娘ＴＤ」運営チームです。\r\n\r\nこのたびは、皆様の応援のもと、無事にアーリーアクセスを開始することができました。\r\n運営一同より、心より感謝を申し上げます。\r\n\r\nご利用の皆様にお楽しみいただけるよう誠心誠意努めてまいりますため、\r\n末永く『モンスター娘ＴＤ』をよろしくお願いいたします。\r\n"
    },
    {
      "id": 2,
      "date": "2022/03/14 13:00",
      "tag": 5,
      "title": "「アーリーアクセス開始記念ログインボーナス」開催！",
      "message": "「モンスター娘ＴＤ」運営チームです。\r\n\r\n2022/03/14（月）より\r\n「アーリーアクセス開始記念ログインボーナス」を開催いたします！"
    },
    {
      "id": 3,
      "date": "2022/03/14 13:00",
      "tag": 3,
      "title": "「アーリーアクセス開始記念ガチャ」開催！",
      "message": "「モンスター娘ＴＤ」運営チームです。\r\n\r\n2022/03/14（月）より\r\n「アーリーアクセス開始記念ガチャ」を開催いたします！"
    },
    {
      "id": 4,
      "date": "2022/03/14 13:00",
      "tag": 3,
      "title": "「人喰い魔獣と女王蜂ガチャ」開催！",
      "message": "「モンスター娘ＴＤ」運営チームです。\r\n\r\n2022/03/14（月）より\r\n「人喰い魔獣と女王蜂ガチャ」を開催いたします！"
    },
    {
      "id": 5,
      "date": "2022/03/14 13:00",
      "tag": 3,
      "title": "「合成魔獣と樹木霊ガチャ」開催！",
      "message": "「モンスター娘ＴＤ」運営チームです。\r\n\r\n2022/03/14（月）より\r\n「合成魔獣と樹木霊ガチャ」を開催いたします！"
    },
    {
      "id": 6,
      "date": "2022/03/14 13:00",
      "tag": 7,
      "title": "「アーリーアクセス開始記念パック」発売！",
      "message": "「モンスター娘ＴＤ」運営チームです。\r\n\r\n2022/03/14（月）より\r\n「アーリーアクセス開始記念パック」パックを販売いたします！"
    },
    {
      "id": 7,
      "date": "2022/03/14 13:00",
      "tag": 4,
      "title": "ウェルカムイベント「ようこそゲシュペンス島」開催！",
      "message": "「モンスター娘ＴＤ」運営チームです。\r\n\r\n2022/03/14（月）より\r\nウェルカムイベント「ようこそゲシュペンス島」を開催いたします！"
    }
  ]
}